energon_prometheus_exporter/prometheus_exporter.py
energon_prometheus_exporter/drivers/UM25C.py
energon_prometheus_exporter/drivers/__ init __.py
energon_prometheus_exporter/drivers/constants.py
energon_prometheus_exporter/drivers/driver.py
energon_prometheus_exporter/drivers/utils.py
energon_prometheus_exporter/models/__ init __.py
energon_prometheus_exporter/models/general_model.py
energon_prometheus_exporter/models/jetson_agx_orin.py
energon_prometheus_exporter/models/jetson_agx_xavier.py
energon_prometheus_exporter/models/jetson_nano_dev_kit.py
energon_prometheus_exporter/models/jetson_orin_nano.py
energon_prometheus_exporter/models/jetson_xavier_dev_kit.py
energon_prometheus_exporter/models/ubuntu_64.py
energon_prometheus_exporter-0.1.0.dist-info/LICENSE
energon_prometheus_exporter-0.1.0.dist-info/METADATA
energon_prometheus_exporter-0.1.0.dist-info/WHEEL
energon_prometheus_exporter-0.1.0.dist-info/top_level.txt
energon_prometheus_exporter-0.1.0.dist-info/RECORD
