Metadata-Version: 2.1
Name: energon_prometheus_exporter
Version: 0.1.0
Summary: Energon is a Prometheus compliant system monitoring tools, it focuses on the energy consumption and resource usage in constrained devices but it integrates reporting tools for desktop machine, too.
Author-email: Matteo Mendula <mattemendu@gmail.com>
Project-URL: Homepage, https://github.com/MatteoMendula/Energon_Prometheus_exporter
Project-URL: Bug Tracker, https://github.com/MatteoMendula/Energon_Prometheus_exporter/issues
Classifier: Programming Language :: Python :: 3
Classifier: License :: OSI Approved :: MIT License
Classifier: Operating System :: OS Independent
Requires-Python: >=3.6
License-File: LICENSE
Requires-Dist: prometheus-client==0.17.0
